tminify/__init__.py
tminify/__main__.py
tminify/cli.py
tminify/main.py
tminify/py.typed
tminify/version.py
tminify/javascript/package.json
tminify-0.1.6.dist-info/METADATA
tminify-0.1.6.dist-info/WHEEL
tminify-0.1.6.dist-info/entry_points.txt
tminify-0.1.6.dist-info/licenses/LICENSE
tminify-0.1.6.dist-info/RECORD
