Metadata-Version: 2.4
Name: tminify
Version: 0.1.6
Summary: Standalone CLI and Python package for modern HTML/CSS/JS/Tailwind minification
Project-URL: Repository, https://github.com/jlevy/tminify
Author-email: Joshua Levy <joshua@cal.berkeley.edu>
License-Expression: MIT
License-File: LICENSE
Classifier: Development Status :: 4 - Beta
Classifier: Intended Audience :: Developers
Classifier: Operating System :: OS Independent
Classifier: Programming Language :: Python
Classifier: Programming Language :: Python :: 3
Classifier: Programming Language :: Python :: 3.11
Classifier: Programming Language :: Python :: 3.12
Classifier: Programming Language :: Python :: 3.13
Classifier: Typing :: Typed
Requires-Python: <4.0,>=3.11
Requires-Dist: prettyfmt>=0.4.0
